xju/assert_.py
xju/assert_.py.test
xju/cmc_mypy_plugin.py
xju/cmd.py
xju/cmd.py.test
xju/json_codec.py
xju/json_codec.py.test
xju/json_codec_mypy_plugin.py
xju/jsonschema.py
xju/jsonschema.py.test
xju/misc.py
xju/misc.py.test
xju/newtype.py
xju/newtype.py.test
xju/patch.py
xju/patch.py.test
xju/pq.py
xju/pq.py.test
xju/py.typed
xju/rfc2616.py
xju/rfc2616.py.test
xju/time.py
xju/time.py.test
xju/xn.py
xju/xn.py.test
xju/xn_mypy_plugin.py
xju/cmc/AsyncDict.py.test
xju/cmc/AsyncOpt.py.test
xju/cmc/AsyncServiceQueue.py.test
xju/cmc/AsyncTaskMutexLockCondition.py.test
xju/cmc/Dict.py.test
xju/cmc/Opt.py.test
xju/cmc/Process.py.test
xju/cmc/ThreadMutexLockCondition.py.test
xju/cmc/__init__.py
xju/cmc/async_cmclass.py.test
xju/cmc/cmc.py.test
xju/cmc/cmclass.py.test
xju/cmc/delay_cancellation.py.test
xju/cmc/perflog.py
xju/cmc/perflog.py.test
xju/cmc/signal.py
xju/cmc/signal.py.test
xju/cmc/sockets.py
xju/cmc/sockets.py.test
xju/cmc/tstore.py
xju/cmc/tstore.py.test
xju/cmc/io/FileLock.py.test
xju/cmc/io/FileMode.py.test
xju/cmc/io/FilePosition.py.test
xju/cmc/io/FileReader.py.test
xju/cmc/io/FileWriter.py.test
xju/cmc/io/Pipe.py.test
xju/cmc/io/UnixStreamSocket.py.test
xju/cmc/io/__init__.py
xju-4.2.0.dist-info/METADATA
xju-4.2.0.dist-info/WHEEL
xju-4.2.0.dist-info/top_level.txt
xju-4.2.0.dist-info/RECORD
