Metadata-Version: 2.2
Name: xju
Version: 4.2.0
Summary: xju library
Author: Trevor Taylor
License: Copyright © 2022 Trevor Taylor
Project-URL: Homepage, https://github.com/urnest/urnest
Classifier: License :: OSI Approved :: MIT License
Classifier: Programming Language :: Python
Classifier: Programming Language :: Python :: 3
Classifier: Development Status :: 5 - Production/Stable
Requires-Python: >=3.11
